cf_speedtest/__init__.py
cf_speedtest/__main__.py
cf_speedtest/locations.py
cf_speedtest/options.py
cf_speedtest/speedtest.py
cf_speedtest-0.1.9.dist-info/LICENSE
cf_speedtest-0.1.9.dist-info/METADATA
cf_speedtest-0.1.9.dist-info/WHEEL
cf_speedtest-0.1.9.dist-info/entry_points.txt
cf_speedtest-0.1.9.dist-info/top_level.txt
cf_speedtest-0.1.9.dist-info/RECORD
