Metadata-Version: 2.1
Name: cf_speedtest
Version: 0.1.9
Summary: Command-line internet speed test
Home-page: https://github.com/12932/cf-speedtest
Author: wilbo007
Author-email: wilbo007@protonmail.ch
License: MIT
Classifier: License :: OSI Approved :: MIT License
Classifier: Programming Language :: Python
Classifier: Programming Language :: Python :: 3.6
Classifier: Programming Language :: Python :: 3.7
Classifier: Programming Language :: Python :: 3.8
Classifier: Programming Language :: Python :: 3.9
Classifier: Programming Language :: Python :: 3.10
Classifier: Programming Language :: Python :: 3.11
Classifier: Programming Language :: Python :: 3.12
Requires-Python: >=3.6.0
License-File: LICENSE
Requires-Dist: requests[socks] >=2.22.0
